gobble/__init__.py
gobble/location.py
gobble/parser.py
gobble-0.1.1.dist-info/top_level.txt
gobble-0.1.1.dist-info/METADATA
gobble-0.1.1.dist-info/DESCRIPTION.rst
gobble-0.1.1.dist-info/metadata.json
gobble-0.1.1.dist-info/WHEEL
gobble-0.1.1.dist-info/RECORD
