Metadata-Version: 2.0
Name: gobble
Version: 0.1.1
Summary: A simpler parsing framework
Home-page: https://github.com/prophile/gobble
Author: Alistair Lynn
Author-email: alistair@alynn.co.uk
License: UNKNOWN
Platform: UNKNOWN
Classifier: Development Status :: 2 - Pre-Alpha
Classifier: Intended Audience :: Developers
Classifier: License :: OSI Approved :: MIT License
Classifier: Operating System :: OS Independent
Classifier: Programming Language :: Python :: 3 :: Only
Classifier: Topic :: Software Development :: Compilers
Classifier: Topic :: Software Development :: Interpreters
Classifier: Topic :: Text Processing
